rawgpy/__init__.py
rawgpy/base.py
rawgpy/collection.py
rawgpy/game.py
rawgpy/rawg.py
rawgpy/user.py
rawgpy/utils.py
rawgpy/data_classes/__init__.py
rawgpy/data_classes/charts.py
rawgpy/data_classes/id_name_slug.py
rawgpy/data_classes/platform_.py
rawgpy/data_classes/rating.py
rawgpy/data_classes/store.py
rawgpy-1.0.3.dist-info/LICENSE
rawgpy-1.0.3.dist-info/METADATA
rawgpy-1.0.3.dist-info/WHEEL
rawgpy-1.0.3.dist-info/top_level.txt
rawgpy-1.0.3.dist-info/RECORD
