Metadata-Version: 2.1
Name: rawgpy
Version: 1.0.3
Summary: RAWG.io python api wrapper
Home-page: https://gitlab.com/laundmo/rawg-python-wrapper
Author: laundmo
Author-email: laurinschmidt2001@gmail.com
License: GPLv3
Project-URL: Documentation, https://rawgpy.readthedocs.io/en/latest/quickstart.html
Platform: UNKNOWN
Classifier: Programming Language :: Python :: 3
Classifier: License :: OSI Approved :: GNU General Public License v3 (GPLv3)
Classifier: Operating System :: OS Independent
